cosmospl/__init__.py
cosmospl/exceptions.py
cosmospl-0.0.16.dist-info/LICENSE
cosmospl-0.0.16.dist-info/METADATA
cosmospl-0.0.16.dist-info/WHEEL
cosmospl-0.0.16.dist-info/top_level.txt
cosmospl-0.0.16.dist-info/RECORD
