Metadata-Version: 2.1
Name: cosmospl
Version: 0.0.16
Summary: An alternative Azure Cosmos library with orjson, polars, and fastapi in mind
Author-email: Dean MacGregor <powertrading121@gmail.com>
Requires-Python: >=3.8
License-File: LICENSE
Requires-Dist: httpx[http2]
Requires-Dist: orjson
Provides-Extra: polars
Requires-Dist: polars; extra == "polars"
Provides-Extra: nest-asyncio
Requires-Dist: nest_asyncio; extra == "nest-asyncio"
